Metadata-Version: 2.4
Name: scdiffeq-analyses
Version: 0.0.2
Summary: Notebooks, figures, files, and helper functions to reproduce the analyses presented in the scDiffEq manuscript.
Home-page: https://github.com/scDiffEq/scdiffeq-analyses
Author: Michael E. Vinyard
Author-email: mvinyard.ai@gmail.com
License: MIT
Classifier: Development Status :: 2 - Pre-Alpha
Classifier: Programming Language :: Python :: 3.9
Classifier: Intended Audience :: Science/Research
Classifier: Topic :: Scientific/Engineering :: Bio-Informatics
Requires-Python: >3.9.0
License-File: LICENSE
Requires-Dist: LARRY-dataset==0.1.0dev5
Dynamic: author
Dynamic: author-email
Dynamic: classifier
Dynamic: description
Dynamic: description-content-type
Dynamic: home-page
Dynamic: license
Dynamic: license-file
Dynamic: requires-dist
Dynamic: requires-python
Dynamic: summary
